data/__init__.py
data/main.py
mynews_bot/__init__.py
mynews_bot-0.1.1.data/scripts/mynews_bot.py
rss_feed/__init__.py
rss_feed/main.py
rss_feed/utils.py
mynews_bot-0.1.1.dist-info/LICENCE
mynews_bot-0.1.1.dist-info/METADATA
mynews_bot-0.1.1.dist-info/WHEEL
mynews_bot-0.1.1.dist-info/entry_points.txt
mynews_bot-0.1.1.dist-info/top_level.txt
mynews_bot-0.1.1.dist-info/RECORD
