Metadata-Version: 2.1
Name: mynews-bot
Version: 0.1.1
Summary: Get news items from multiple news sources
Home-page: https://github.com/rajarshig/mynews_bot
Author: Rajarshi Ghosh
Author-email: rajarshig89@gmail.com
License: UNKNOWN
Keywords: python,command-line,rss feed
Platform: any
Classifier: Environment :: Web Environment
Classifier: Intended Audience :: Developers
Classifier: License :: OSI Approved :: BSD License
Classifier: Operating System :: OS Independent
Classifier: Programming Language :: Python
Classifier: Programming Language :: Python :: 3
Classifier: Topic :: Internet :: WWW/HTTP :: Dynamic Content
Classifier: Topic :: Software Development :: Libraries :: Python Modules
Requires-Python: >=2.7
Requires-Dist: feedparser
